CHANGES
Copyright
README
setup.cfg
setup.py
ZSI/.cvsignore
ZSI/LBNLCopyright
ZSI/ServiceContainer.py
ZSI/ServiceProxy.py
ZSI/TC.py
ZSI/TCapache.py
ZSI/TCcompound.py
ZSI/TCnumbers.py
ZSI/TCtimes.py
ZSI/__init__.py
ZSI/address.py
ZSI/auth.py
ZSI/client.py
ZSI/digest_auth.py
ZSI/dispatch.py
ZSI/fault.py
ZSI/parse.py
ZSI/resolvers.py
ZSI/schema.py
ZSI/typeinterpreter.py
ZSI/version.py
ZSI/writer.py
ZSI/generate/__init__.py
ZSI/generate/commands.py
ZSI/generate/containers.py
ZSI/generate/pyclass.py
ZSI/generate/utility.py
ZSI/generate/wsdl2dispatch.py
ZSI/generate/wsdl2python.py
ZSI/twisted/WSresource.py
ZSI/twisted/WSsecurity.py
ZSI/twisted/__init__.py
ZSI/twisted/client.py
ZSI/twisted/interfaces.py
ZSI/twisted/reverse.py
ZSI/twisted/wsgi.py
ZSI/wstools/.cvsignore
ZSI/wstools/MIMEAttachment.py
ZSI/wstools/Namespaces.py
ZSI/wstools/TimeoutSocket.py
ZSI/wstools/UserTuple.py
ZSI/wstools/Utility.py
ZSI/wstools/WSDLTools.py
ZSI/wstools/XMLSchema.py
ZSI/wstools/XMLname.py
ZSI/wstools/ZPL
ZSI/wstools/__init__.py
ZSI/wstools/c14n.py
ZSI/wstools/license.txt
ZSI/wstools/logging.py
ZSI/wstools/test/.cvsignore
ZSI/wstools/test/README
ZSI/wstools/test/__init__.py
ZSI/wstools/test/config.txt
ZSI/wstools/test/schema.tar.gz
ZSI/wstools/test/test_t1.py
ZSI/wstools/test/test_wsdl.py
ZSI/wstools/test/test_wstools.py
ZSI/wstools/test/test_wstools_net.py
ZSI/wstools/test/xmethods.tar.gz
doc/.cvsignore
doc/blank.png
doc/contents.png
doc/index.png
doc/modules.png
doc/next.png
doc/previous.png
doc/pyfav.png
doc/up.png
doc/zsi.xsd
doc/examples/client/receive_response/complex/binding.wsdl
doc/examples/client/receive_response/complex/interface.wsdl
doc/examples/client/receive_response/complex/types.xsd
doc/examples/client/receive_response/complex/manual/.cvsignore
doc/examples/client/receive_response/complex/manual/ComplexTypes.py
doc/examples/client/receive_response/complex/manual/client.py
doc/examples/client/receive_response/complex/server/.cvsignore
infi.ZSI.egg-info/PKG-INFO
infi.ZSI.egg-info/SOURCES.txt
infi.ZSI.egg-info/dependency_links.txt
infi.ZSI.egg-info/entry_points.txt
infi.ZSI.egg-info/top_level.txt
